uniprot_cli/__init__.py
uniprot_cli/datasources.py
uniprot_cli/dispatcher.py
uniprot_cli/fetcher.py
uniprot_cli/writer.py
uniprot_cli-0.3.4.dist-info/LICENSE
uniprot_cli-0.3.4.dist-info/METADATA
uniprot_cli-0.3.4.dist-info/WHEEL
uniprot_cli-0.3.4.dist-info/entry_points.txt
uniprot_cli-0.3.4.dist-info/top_level.txt
uniprot_cli-0.3.4.dist-info/RECORD
