Metadata-Version: 2.1
Name: uniprot-cli
Version: 0.3.4
Summary: An unofficial client for uniprot.
Author-email: HackTheOxidation <tomas.hagenau@protonmail.ch>
License: Copyright (c) 2022 HackTheOxidation        
Project-URL: Homepage, https://codeberg.org/HackTheOxidation/uniprot_cli
Project-URL: Bug Tracker, https://codeberg.org/HackTheOxidation/uniprot_cli/issues
Classifier: Programming Language :: Python :: 3
Classifier: License :: OSI Approved :: MIT License
Classifier: Operating System :: OS Independent
Requires-Python: >=3.8
License-File: LICENSE
Requires-Dist: requests
